LICENSE.txt
MANIFEST.in
README.rst
setup.cfg
setup.py
gmtasks/__init__.py
gmtasks/jsonclass.py
gmtasks.egg-info/PKG-INFO
gmtasks.egg-info/SOURCES.txt
gmtasks.egg-info/dependency_links.txt
gmtasks.egg-info/requires.txt
gmtasks.egg-info/top_level.txt