Metadata-Version: 1.1
Name: gmtasks
Version: 0.4
Summary: Gearman Task Server
Home-page: https://github.com/ex-nerd/gmtasks
Author: Chris Petersen
Author-email: geek@ex-nerd.com
License: Modified BSD
Platform: UNKNOWN
Classifier: Development Status :: 3 - Alpha
Classifier: Environment :: Web Environment
Classifier: Intended Audience :: Developers
Classifier: License :: OSI Approved :: BSD License
Classifier: Operating System :: OS Independent
Classifier: Programming Language :: Python
Classifier: Topic :: Utilities
